CNLTK/NER_TAGGER_MODEL.py
CNLTK/NER_test.py
CNLTK/POS_MODEL.py
CNLTK/POS_NER_tags.py
CNLTK/POS_TAGGER_MODEL.py
CNLTK/POS_test.py
CNLTK/__init__.py
CNLTK/attention.py
CNLTK/ceb_corpus.py
CNLTK/config.ini
CNLTK/config.py
CNLTK/config_files.py
CNLTK/pos_tags.py
CNLTK/preprocessing.py
CNLTK/requirements.txt
CNLTK/vocabulary.py
CNLTK/Datasets/annotatedtestxt.csv
CNLTK/NER/NER_MODEL.py
CNLTK/NER/NER_TAGGER_MODEL.py
CNLTK/NER/NER_test.py
CNLTK/NER/ner_tags.py
CNLTK/models/NER_WORD(1).h5
CNLTK/models/POS_TAG_WORD(1).h5
CNLTK/models/ner_tagindex_model.pkl
CNLTK/models/tagindex_model.pkl
CNLTK/models/vocab_model2.pkl
CNLTK_Beta-1.1.dist-info/LICENCE.txt
CNLTK_Beta-1.1.dist-info/METADATA
CNLTK_Beta-1.1.dist-info/WHEEL
CNLTK_Beta-1.1.dist-info/top_level.txt
CNLTK_Beta-1.1.dist-info/RECORD
